<TEST NAME="Test_4" FILE="calculator.py">

 <VERSION NUMBER="1" CHECKED="TRUE">
   <LOCATION ORIG="1" NEW="1" />
   <LOCATION ORIG="2" NEW="2" />
   <LOCATION ORIG="3" NEW="3" />
   <LOCATION ORIG="4" NEW="4" />
   <LOCATION ORIG="5" NEW="5" />
   <LOCATION ORIG="6" NEW="6" />
   <LOCATION ORIG="7" NEW="7" />
   <LOCATION ORIG="8" NEW="8" />
   <LOCATION ORIG="9" NEW="9" />
   <LOCATION ORIG="10" NEW="10" />
   <LOCATION ORIG="11" NEW="11" />
   <LOCATION ORIG="12" NEW="12" />
   <LOCATION ORIG="13" NEW="13" />
   <LOCATION ORIG="14" NEW="14" />
   <LOCATION ORIG="15" NEW="15" />
 </VERSION>

 <VERSION NUMBER="2" CHECKED="TRUE">
   <LOCATION ORIG="-1" NEW="2" />
   <LOCATION ORIG="2" NEW="3" />
   <LOCATION ORIG="4" NEW="4" />
   <LOCATION ORIG="5" NEW="5" />
   <LOCATION ORIG="7" NEW="6" />
   <LOCATION ORIG="8" NEW="7" />
   <LOCATION ORIG="-1" NEW="10" />
   <LOCATION ORIG="10" NEW="11" />
   <LOCATION ORIG="16" NEW="12" />
   <LOCATION ORIG="19" NEW="-1" />
   <LOCATION ORIG="17" NEW="13" />
   <LOCATION ORIG="18" NEW="14" />
   <LOCATION ORIG="22" NEW="-1" />
 </VERSION>

</TEST>
